{
  "concerts": [
    {
      "artist": "Ca7riel & Paco Amoroso",
      "date": "4-11-2025",
      "venue": "Columbiahalle, Berlin",
      "image": "ca7riel.jpg",
      "description": "Went with Victor and we were wowed by their insane energy. It was jam-packed and the crowd went wild for them. They played the Sims music as they came on stage!",
      "id": "e71dcc9e-2878-42af-9de9-01471d737adc",
      "newsletter": true
    },
    {
      "artist": "Perfume Genius",
      "date": "3-11-2025",
      "venue": "Astra Kulturhaus, Berlin",
      "image": "perfume-genius.jpg",
      "description": "Second time seeing them, again with Sam. Some great moments. They played a deep cut from 'Ugly Season' that I love.",
      "id": "d192cab6-a9f3-450b-a652-cf4ec74e82b2",
      "newsletter": true
    },
    {
      "artist": "Cuntine",
      "date": "17-10-2025",
      "venue": "Supamolly, Berlin",
      "image": "cuntine.jpg",
      "description": "Awesome lesbian punk band from a friend of Tobias. Beaten only by the warm-up band 'PMS Hit Fabrik'. I'll never forget it. Tragically I have no pictures from the event.",
      "id": "07ebe6f8-56d2-4529-9448-c9f8b36247db",
      "newsletter": true
    },
    {
      "artist": "clipping.",
      "date": "16-09-2025",
      "venue": "Gretchen, Berlin",
      "image": "clipping.jpg",
      "description": "Went with anni to this incredible music from this horror/hip-hop genreless band. Shoutouts to their guest singer Sharon Stone and also this girl who filmed with her 3DS.",
      "id": "795b60be-3068-4eef-8de5-ea5b820c4fab",
      "newsletter": true
    },
    {
      "artist": "G'emma",
      "date": "10-09-2025",
      "venue": "Monarch Bar, Berlin",
      "image": "gemma.jpg",
      "description": "Susi's sister! This is the second time seeing her and it was great.",
      "id": "7f3bbb9d-646f-4097-aa28-fe34d5f8dfb5",
      "newsletter": true
    },
    {
      "artist": "Arm",
      "date": "30-08-2025",
      "venue": "Teepeeland, Berlin",
      "image": "arm.jpg",
      "description": "My mate Rodrigo has a band and this was their first ever concert! It was sick. They play jazz fusion with wild time signatures. Tragically I did not take a picture.",
      "id": "d9a8a5fb-b49a-4a50-94d2-9c13bd336f66",
      "newsletter": true
    },
    {
      "artist": "St. Vincent",
      "date": "05-07-2025",
      "venue": "Tempodrom, Berlin",
      "image": "st-vincent.PNG",
      "description": "Wow I didn't understand what a fun diva she is until this concert! One of the best ever. Went with Victor.",
      "id": "9f988163-fe25-4adf-9d1f-e454949614b9",
      "newsletter": true
    },
    {
      "artist": "Spellling",
      "date": "16-06-2025",
      "venue": "Lido, Berlin",
      "image": "spellling.PNG",
      "description": "I love Spellling and seeing her live was great! I also got to meet her at the merch stand and she called me extra for being sassy about them not selling CDs. I went alone but bumped into my old friend Boris there.",
      "id": "da1b4f0f-e763-49c6-937f-eda445c3ab75",
      "newsletter": true
    },
    {
      "artist": "Tunng",
      "date": "09-03-2025",
      "venue": "Silent Green, Berlin",
      "image": "tunng.jpeg",
      "description": "Solo trip to see an old band I used to love 15 years ago. It was nice to hear them play all their old tracks and I got to meet the guy.",
      "id": "dff4e5ad-f5b7-4c2d-a5bc-66758650d17b",
      "newsletter": true
    },
    {
      "artist": "Confidence Man",
      "date": "02-18-2025",
      "venue": "Berghain Kantine, Berlin",
      "image": "confidence-man.PNG",
      "description": "A concert-length dance routine from these two. A lot of fun. Only regret was that we queued in the freezing cold for the main Berghain before realising it was Berghain Kantine.",
      "id": "b843f28b-72fe-4396-a432-6431e58ed476",
      "newsletter": true
    },
    {
      "artist": "Magdalena Bay",
      "date": "09-11-2024",
      "venue": "Columbia Theater, Berlin",
      "image": "magdalena-bay.jpg",
      "description": "I was late to this because I'm an idiot and I'm still kicking myself about it. They played one of my favourite albums 'Imaginal disk' all the way through and it was amazing.",
      "id": "298e641b-24ff-4b8d-81dd-b229908f3828",
      "newsletter": true
    },
    {
      "artist": "Khruangbin",
      "date": "07-11-2024",
      "venue": "Tempodrom, Berlin",
      "image": "khruangbin.jpg",
      "description": "Great to see these guys live with Victor and Blanca. They played their album 'A la sala' as well as a bunch of classics.",
      "id": "29d1c62c-7532-4f58-89cd-35ce77a35e2f",
      "newsletter": true
    },
    {
      "artist": "Fat Dog",
      "date": "16-10-2024",
      "venue": "Urban Spree, Berlin",
      "image": "fat-dog.jpg",
      "description": "Only have this image of the warmup band, but they were great. Unpolished rock music with a mosh pit. The electricity went out at some point.",
      "id": "5071b47a-7a92-4d1c-9eac-8c09d0be1f68",
      "newsletter": true
    },
    {
      "artist": "Air",
      "date": "21-07-2024",
      "venue": "Zitadelle Spandau, Berlin",
      "image": "air.jpg",
      "description": "Fuck this location, we weren't allowed to stand up?? Air played Moon Safari, a classic album, but literally just played the songs as is with no stage banter between.",
      "id": "9d082172-eb57-4bca-a7b1-d025bb7f64b4",
      "newsletter": true
    },
    {
      "artist": "Sessa",
      "date": "19-07-2024",
      "venue": "Humboldt Forum, Berlin",
      "image": "sessa.jpg",
      "description": "A free concert from this very chill Brazilian artist that I've been following for a bit. Turned out to be a nice activity for a friend who was having a bad day.",
      "id": "c2ee80c5-1cbe-46db-867f-75578f02de51",
      "newsletter": true
    },
    {
      "artist": "Anohni and the Johnsons",
      "date": "09-07-2024",
      "venue": "Zitadelle Spandau, Berlin",
      "image": "anohni.jpg",
      "description": "Wow, one of the most sublime concerts ever. She gave an amazing political speech during it. The arrangements were stunning. But fuck this venue, we weren't allowed to go near the seats. I went on my own and met a really hot guy there.",
      "id": "fa51aa1f-6e1c-49c0-862f-ce67f54374f1",
      "newsletter": true
    },
    {
      "artist": "Django Django",
      "date": "21-11-2023",
      "venue": "Festsaal Kreuzberg, Berlin",
      "image": "django-django.webp",
      "description": "Nerdy band from Scotland that I've been a fan of for a while. They played all their old songs, it was great! Bumped into my friend Uzay there.",
      "id": "4cb4f7a2-9b54-4f6e-8c94-a5c4535d9fab",
      "newsletter": true
    },
    {
      "artist": "Timber Timbre",
      "date": "06-11-2023",
      "venue": "Festsaal Kreuzberg, Berlin",
      "image": "timber-timbre.jpg",
      "description": "The artist asked the audience not to take pictures and video but everyone did it anyway. Weird vibes during the concert! I got this snap at the start.",
      "id": "ea7356ec-b6c8-4424-9c72-226baac83a60",
      "newsletter": true
    },
    {
      "artist": "Erlend Øye & La Comitiva",
      "date": "25-08-2023",
      "venue": "Freilichtbühne Weißensee, Berlin",
      "image": "erlend-oye.jpg",
      "description": "Maitén invited me to this and I loved it so much more than I thought I would!",
      "id": "d186e83d-2949-49ce-b71f-a1bebbb45a46",
      "newsletter": true
    },
    {
      "artist": "G'emma",
      "date": "13-07-2023",
      "venue": "Monarch Bar, Berlin",
      "image": "gemma2.jpg",
      "description": "Susi's sister! I didn't know her before this but was blown away she is so cool and the concert was great.",
      "id": "d186e83d-2949-49ce-b71f-a1bebbb45a46",
      "newsletter": true
    },
    {
      "artist": "Silvana Estrada",
      "date": "05-06-2023",
      "venue": "Hole 44, Berlin",
      "image": "silvana.PNG",
      "description": "Bigger concert, don't love the location, but she was amazing. Went with Ort and new friends.",
      "id": "0a006ee8-2d68-4e0e-8c88-79f6c2e39fe9",
      "newsletter": true
    },
    {
      "artist": "The Tallest Man on Earth",
      "date": "01-05-2023",
      "venue": "Metropol, Berlin",
      "image": "tallest.PNG",
      "description": "This was really nice as always, although nothing will live up to the previous concert he did which was perfect.",
      "id": "6b7ace7c-af58-4151-8def-ca98b56639f1",
      "newsletter": true
    },
    {
      "artist": "Caroline Polachek",
      "date": "22-02-2023",
      "venue": "Huxley's Neue Welt, Berlin",
      "image": "caroline.PNG",
      "description": "Best pop concert ever with Sam, Kitty and Ale. Queer crowd and I loved it when she sang my favourite song 'Billions'.",
      "id": "a1702f5e-263f-4740-b1f8-22297fa55fdc",
      "newsletter": true
    },
    {
      "artist": "Weyes Blood",
      "date": "28-01-2023",
      "venue": "Astra Kulturhaus, Berlin",
      "image": "weyes-blood.PNG",
      "description": "Beautiful, amazing, stunning, I love her. Went on my own and had a moment during 'God turn me into a flower'.",
      "id": "59b3a9fa-7c21-42b1-801b-b6a6a010b3a8",
      "newsletter": true
    },
    {
      "artist": "Kimbra",
      "date": "22-01-2023",
      "venue": "Hole 44, Berlin",
      "image": "kimbra.jpg",
      "description": "Bit of an awkward concert. She was visibly insecure and her bandmates weren't vibing with her. Venue isn't great.",
      "id": "c0cda234-94e1-4e3c-91e3-c66da26eafdc",
      "newsletter": true
    },
    {
      "artist": "Jockstrap",
      "date": "31-10-2022",
      "venue": "Baketown, Berlin",
      "image": "jockstrap.jpg",
      "description": "Great music in a teeny-tiny venue where I couldn't see the band! I met them after though.",
      "id": "8ec85860-0adf-4395-9a49-36132ed3791e",
      "newsletter": true
    },
    {
      "artist": "Marcos Valle",
      "date": "18-10-2022",
      "venue": "Gretchen, Berlin",
      "image": "marcos-valle.PNG",
      "description": "Loved this crowd consisting of middle aged Brazilian women and young queer white people. He was awesome. Went with new friend Mathis!",
      "id": "8ec85860-0adf-4395-9a49-36132ed3791e",
      "newsletter": true
    },
    {
      "artist": "Hiatus Kaiyote",
      "date": "29-09-2022",
      "venue": "Huxley's Neue Welt, Berlin",
      "image": "haitus-kaiyote.PNG",
      "description": "Went with Suzanne and Ort and Diego. They just played their songs normally without much stage banger. Diego got super high from my pipe and I still feel bad about it.",
      "id": "a15292bf-0297-41b5-b002-e8939eb78210",
      "newsletter": true
    },
    {
      "artist": "Fleet Foxes",
      "date": "11-09-2022",
      "venue": "Columbiahalle, Berlin",
      "image": "fleet-foxes.PNG",
      "description": "It was alright but they just played there songs one after the other, no surprises.",
      "id": "ea6c09cf-b041-4cc2-ac84-cf464b329063",
      "newsletter": true
    },
    {
      "artist": "Perfume Genius",
      "date": "16-08-2022",
      "venue": "Metropol, Berlin",
      "image": "perfume-genius2.jpg",
      "description": "Went here with Sam and it was amazing! One of the best concerts! I'll never forget the song 'Photograph'",
      "id": "ce25e7fe-349a-4bc9-a012-512cc8023582",
      "newsletter": true
    },
    {
      "artist": "Silvana Estrada",
      "date": "06-07-2022",
      "venue": "Aeden, Berlin",
      "image": "silvana2.jpg",
      "description": "Wow! This turned me from a fan into a mega-fan. Cute, tiny concert for such a big star! This is also where I became friends with Ort.",
      "id": "1a617144-26c2-4eb8-b19d-32405a116b42",
      "newsletter": true
    },
    {
      "artist": "Magdalena Bay",
      "date": "14-06-2022",
      "venue": "Urban Spree, Berlin",
      "image": "magdalena-bay2.jpg",
      "description": "Loved this concert! Jack and I went although it was way to loud volume-wise. I got to meet them after!",
      "id": "cfa6cf53-f808-47fa-9712-d11b00e16826",
      "newsletter": true
    },
    {
      "artist": "Kings of Convenience",
      "date": "08-06-2022",
      "venue": "Admiralspalast, Berlin",
      "image": "kings-of-convenicen.jpeg",
      "description": "Mortified because I arrived late to this and it was a fancy sit-down venue. Also I ate an edible and got way too high during the concert.",
      "id": "858cfdc1-50a6-4234-922a-ca37a0cd14e5",
      "newsletter": true
    },
    {
      "artist": "Dorian Electra",
      "date": "25-04-2022",
      "venue": "Gretchen, Berlin",
      "image": "dorian.PNG",
      "description": "Put on make-up with Sam to look extra non-binary for this concert! Highlights were warm up act Lil Mariko and being complimented on my kero kero bonito shirt.",
      "id": "cf1deb10-d8a2-47db-9ea9-fb0f54f6bb69",
      "newsletter": true
    },
    {
      "artist": "The Tallest Man on Earth",
      "date": "20-04-2022",
      "venue": "Heimathafen Neukölln, Berlin",
      "image": "tallest2.PNG",
      "description": "One of my all-time favourite concerts. I'm a mega fan and he played all my favourite songs. Afterwards I got to hang out with him and share a drink!",
      "id": "f46f762d-b81d-4687-896d-ed59643fedb5",
      "newsletter": true
    },
    {
      "artist": "Khruangbin",
      "date": "07-04-2022",
      "venue": "Columbiahalle, Berlin",
      "image": "khruangbin2.webp",
      "description": "Incredible concert! I went alone but it turns out loads of my friends were there that day. I loved the reveal of her outfit.",
      "id": "83cab167-8cab-40b2-87f9-ba64707614ac",
      "newsletter": true
    },
    {
      "artist": "Jordan Rakei",
      "date": "04-04-2022",
      "venue": "Festsaal Kreuzberg, Berlin",
      "image": "jordan-rakei.PNG",
      "description": "I remember looking at the crowd and thinking this is soul music for white people.",
      "id": "9fc26d4d-ccbc-4d31-8162-a9aa65088ffa",
      "newsletter": true
    },
    {
      "artist": "Polo & Pan",
      "date": "23-03-2022",
      "venue": "Metropol, Berlin",
      "image": "polo-pan.jpg",
      "description": "Dance music from this French duo I like. Went for a controversial top floor at Metropol and it wasn't too bad.",
      "id": "f0df61d6-a0c7-4929-9a3b-57174fe13a3e",
      "newsletter": true
    },
    {
      "artist": "Systemabsturz",
      "date": "12-11-2021",
      "venue": "C-Base, Berlin",
      "image": "systemabsturz.PNG",
      "description": "Release party for this local band, loved it! They played 'Verdächtig' twice.",
      "id": "7aac8ca2-f301-40e8-8d3d-33d3e89186b1",
      "newsletter": true
    },
    {
      "artist": "Snarky Puppy",
      "date": "29-10-2019",
      "venue": "Columbiahalle, Berlin",
      "image": "snarky-puppy.PNG",
      "description": "These days I struggle with this band but they did play 'Whitecap' which is my fave. I respect that they have a different set every show.",
      "id": "8a0918ab-c5bf-42d2-bbc0-bfbd005ea6b8",
      "newsletter": true
    },
    {
      "artist": "Janelle Monáe",
      "date": "09-07-2019",
      "venue": "Columbiahalle, Berlin",
      "image": "janelle-monae.PNG",
      "description": "She was honestly great and I'm a mega fan. We got on our knees and she briefly sang Violet Stars.",
      "id": "6417d0c1-3b71-4175-956e-55070edde11f",
      "newsletter": true
    },
    {
      "artist": "Erykah Badu",
      "date": "05-06-2019",
      "venue": "Verti Music Hall",
      "image": "erykah.PNG",
      "description": "A legend! Loved this concert even though there was a special cordoned off bit at the front of the crowd for expensive tickets, kinda lame.",
      "id": "67e759a2-3576-42fc-acb1-6c3b66b081c6",
      "newsletter": true
    },
    {
      "artist": "L'impératrice",
      "date": "30-05-2019",
      "venue": "Hole 44, Berlin",
      "image": "limperatrice.PNG",
      "description": "Awesome concert with awesome songs. I should go listen to them right now.",
      "id": "91a32ae1-6c0a-46a4-8c15-2dd4e0e9d296",
      "newsletter": true
    },
    {
      "artist": "Noname",
      "date": "13-04-2019",
      "venue": "Gretchen, Berlin",
      "image": "noname.PNG",
      "description": "Went to see her right as she started complaining about white audiences! Am I the problem? (It was an amazing concert)",
      "id": "b3b303a6-b4c3-4abb-b5d9-20bdb347380f",
      "newsletter": true
    },
    {
      "artist": "Saba",
      "date": "05-03-2019",
      "venue": "Lido, Berlin",
      "image": "saba.PNG",
      "description": "Felt a bit out of place at a hip-hop concert but I went with Marco and it was a great experience.",
      "id": "ac7b7c5e-deac-4c6b-9b95-2607df98dc37",
      "newsletter": true
    },
    {
      "artist": "Kero Kero Bonito",
      "date": "28-11-2018",
      "venue": "Monarch Bar, Berlin",
      "image": "kero.PNG",
      "description": "An all-time favourite concert. It was WILD! There was a moshpit and I saw people doing coke on the dancefloor (which for me at the time was an eye-opener).",
      "id": "cb4f7b25-c247-417b-b916-1d2651cd4254",
      "newsletter": true
    },
    {
      "artist": "Honne",
      "date": "05-11-2018",
      "venue": "Astra Kulturhaus, Berlin",
      "image": "honne.PNG",
      "description": "I realised that maybe they're not as good as I thought they were. They made you hug a neighbour in their song 'Woman' but when I did it, it was weird and I felt awkward for going there alone.",
      "id": "d38d094e-42eb-4a6d-87ed-c8b2b5237ed6",
      "newsletter": true
    },
    {
      "artist": "Olafur Arnalds",
      "date": "11-10-2018",
      "venue": "Tempodrom, Berlin",
      "image": "olafur.jpg",
      "description": "Went with Lucas, it was alright! I wasn't a huge fan but it was a nice concert.",
      "id": "17621b4d-2761-4168-962c-c68cdba2d4f4",
      "newsletter": true
    },
    {
      "artist": "Noname",
      "date": "14-08-2018",
      "venue": "Lido, Berlin",
      "image": "noname2.PNG",
      "description": "Amazing concert not least because the warm up act was Sampa the Great!",
      "id": "5134744a-317d-41f3-83a5-d8e8158d1466",
      "newsletter": true
    },
    {
      "artist": "Bonobo",
      "date": "26-05-2018",
      "venue": "Velodrom, Berlin",
      "image": "bonobo.PNG",
      "description": "Big budget show with lots of lights and sounds! I didn't love love love this concert.",
      "id": "47dfa0a1-ed3c-41df-9740-186f1f188725",
      "newsletter": true
    },
    {
      "artist": "Rhye",
      "date": "30-03-2018",
      "venue": "Funkhaus, Berlin",
      "image": "rhye.jpg",
      "description": "Loved this concert! I went with Mariana and we both had a huge edible before it. Very fond memories.",
      "id": "31459d22-287f-4d8b-bbc8-fb78b40a7978",
      "newsletter": true
    },
    {
      "artist": "Tom Misch",
      "date": "20-03-2018",
      "venue": "Kesselhaus, Berlin",
      "image": "tom-misch.jpg",
      "description": "I remember feeling weird about going here alone and I realised it's totally cool.",
      "id": "0ca0b661-33a9-45e1-aa55-96c1ea75e396",
      "newsletter": true
    },
    {
      "artist": "Snarky Puppy",
      "date": "23-05-2017",
      "venue": "Substage, Karlsruhe",
      "image": "snarky-puppy2.PNG",
      "description": "Really enjoyed this one, although I don't love this band so much these days. It was nice to travel to Karlsruhe with friends.",
      "id": "6b24c666-aa60-4d36-a497-6cd20594b65b",
      "newsletter": true
    },
    {
      "artist": "Laura Marling",
      "date": "04-05-2015",
      "venue": "Guildhall, Southampton",
      "image": "laura.PNG",
      "description": "She was touring her album 'Short Movie' which isn't my favourite. I remember she wore a beautiful flower dress.",
      "id": "19939812-743f-41de-8596-3df5176393be",
      "newsletter": true
    },
    {
      "artist": "Stornoway",
      "date": "21-04-2015",
      "venue": "Engine Rooms, Southampton",
      "image": "stornoway.PNG",
      "description": "Went on my own to this and felt really bad and awkward about it.",
      "id": "19939812-743f-41de-8596-3df5176393be",
      "newsletter": true
    },
    {
      "artist": "The Tallest Man on Earth",
      "date": "27-11-2013",
      "venue": "Fri-Son, Fribourg",
      "image": "tallest4.PNG",
      "description": "One of my all-time faves coming to the tiny town in Switzerland where I was living? Hell yeah.",
      "id": "19939812-743f-41de-8596-3df5176393be",
      "newsletter": true
    },
    {
      "artist": "Tunng",
      "date": "14-11-2013",
      "venue": "Fri-Son, Fribourg",
      "image": "tunng2.jpg",
      "description": "Awesome that they came to Fribourg! I remember that the venue wasn't very full at all.",
      "id": "19939812-743f-41de-8596-3df5176393be",
      "newsletter": true
    },
    {
      "artist": "Laura Marling",
      "date": "14-03-2012",
      "venue": "Guildhall, Southampton",
      "image": "laura2.PNG",
      "description": "Don't remember too much about it apart from loving it.",
      "id": "19939812-743f-41de-8596-3df5176393be",
      "newsletter": true
    },
    {
      "artist": "The Leisure Society",
      "date": "08-12-2011",
      "venue": "The Barbican, London",
      "image": "leisure-society.PNG",
      "description": "I dragged my friend all the way to London to watch my favourite band at the time perform with a full orchestra! It was amazing!",
      "id": "19939812-743f-41de-8596-3df5176393be",
      "newsletter": true
    },
    {
      "artist": "Stornoway",
      "date": "03-09-2011",
      "venue": "The Regal, Oxford",
      "image": "stornoway2.PNG",
      "description": "Formative concert with best friend Oscar from childhood! It's a core memory, the heat, the giant dangerous bouncy ball, the drive home.",
      "id": "19939812-743f-41de-8596-3df5176393be",
      "newsletter": true
    },
    {
      "artist": "The Tallest Man on Earth",
      "date": "15-03-2010",
      "venue": "Bush Hall, London",
      "image": "tallest3.PNG",
      "description": "Loved loved loved hearing this rendition of 'Where do my bluebird fly?'. A lovely trip to London with Oscar.",
      "id": "19939812-743f-41de-8596-3df5176393be",
      "newsletter": true
    }
  ]
}